{"P2": {"labels": ["\u5143\u7b14\u8bb0"], "postTitle": "\u6784\u5efa\u5c5e\u4e8e\u4f60\u7684\u5b66\u4e60\u6700\u5c0f\u95ed\u73af", "postUrl": "post/gou-jian-shu-yu-ni-de-xue-xi-zui-xiao-bi-huan.html", "createdDate": "2024-09-24", "dateLabelColor": "#bc4c00"}, "P1": {"labels": ["\u5730\u7406\u5b66"], "postTitle": "\u5229\u7528\u5ba2\u89c2\u8fd0\u884c\u6cd5\u8ba1\u7b97\u533a\u57df\u5e73\u5747\u964d\u6c34\u91cf\u7684\u65b9\u6cd5", "postUrl": "post/li-yong-ke-guan-yun-xing-fa-ji-suan-qu-yu-ping-jun-jiang-shui-liang-de-fang-fa.html", "createdDate": "2024-09-16", "dateLabelColor": "#bc4c00"}, "labelColorDict": {"\u5143\u7b14\u8bb0": "#c2e0c6", "\u5730\u7406\u5b66": "#1d76db"}}